square_model_client/__init__.py
square_model_client/model_client.py
square_model_client-0.0.10.dist-info/METADATA
square_model_client-0.0.10.dist-info/WHEEL
square_model_client-0.0.10.dist-info/top_level.txt
square_model_client-0.0.10.dist-info/RECORD
