Metadata-Version: 2.1
Name: square-model-client
Version: 0.0.10
Summary: UNKNOWN
Home-page: https://github.com/UKP-SQuARE/square-model-client
Author: UKP
Author-email: baumgaertner@ukp.informatik.tu-darmstadt.de
License: MIT
Download-URL: https://github.com/UKP-SQuARE/square-model-client/archive/refs/tags/v0.0.10.tar.gz
Platform: UNKNOWN
Requires-Dist: aiohttp (>=3.8.3)
Requires-Dist: numpy (>=1.21.6)
Requires-Dist: square-auth (==0.0.14)
